<annotation>
  <folder>abgimg</folder>
  <filename>image-0547</filename>
  <path>C:\Users\KayaDev-Badri\abgimg\image-0547.jpg</path>
  <source>
    <database>Unknown</database>
  </source>
  <size>
    <width>1280</width>
    <height>720</height>
    <depth>3</depth>
  </size>
  <segmented>0</segmented>
  <object>
    <name>person</name>
    <pose>Unspecified</pose>
    <truncated>0</truncated>
    <difficult>0</difficult>
    <bndbox>
      <xmin>1079</xmin>
      <ymin>449</ymin>
      <xmax>1126</xmax>
      <ymax>498</ymax>
    </bndbox>
  </object>
  <object>
    <name>light_motor_vehicle</name>
    <pose>Unspecified</pose>
    <truncated>0</truncated>
    <difficult>0</difficult>
    <bndbox>
      <xmin>20</xmin>
      <ymin>406</ymin>
      <xmax>206</xmax>
      <ymax>598</ymax>
    </bndbox>
  </object>
</annotation>
